mypypisearch/__init__.py
mypypisearch/__main__.py
mypypisearch/main.py
mypypisearch/re_constants.py
mypypisearch/result_item.py
mypypisearch/search.py
mypypisearch-1.3.6.dist-info/LICENSE
mypypisearch-1.3.6.dist-info/METADATA
mypypisearch-1.3.6.dist-info/WHEEL
mypypisearch-1.3.6.dist-info/entry_points.txt
mypypisearch-1.3.6.dist-info/top_level.txt
mypypisearch-1.3.6.dist-info/RECORD
