Metadata-Version: 2.1
Name: mypypisearch
Version: 1.3.6
Summary: Replacement of temporarily deprecated pip search command
Home-page: https://github.com/Creative-Media-Group/mypypisearch
Author: tct123
Author-email: tct1234@protonmail.com
Classifier: Programming Language :: Python :: 3
Classifier: License :: OSI Approved :: MIT License
Classifier: Operating System :: OS Independent
Requires-Python: >=3.8
License-File: LICENSE
Requires-Dist: certifi
Requires-Dist: chardet
Requires-Dist: idna
Requires-Dist: requests
Requires-Dist: tabulate
